[{"timestamp":0.0,"scenario_goals":[{"goal_type":"Traffic","flow_uid":5109,"goal_set":"Video","hold_period":20,"requirements":{"max_latency_s":3.0,"min_throughput_bps":480060.0}},{"goal_type":"Traffic","flow_uid":5110,"goal_set":"Web","hold_period":20,"requirements":{"file_transfer_deadline_s":0.5}},{"goal_type":"Traffic","flow_uid":5111,"goal_set":"Video","hold_period":20,"requirements":{"max_latency_s":3.0,"min_throughput_bps":480060.0}},{"goal_type":"Traffic","flow_uid":5112,"goal_set":"Web","hold_period":20,"requirements":{"file_transfer_deadline_s":0.5}},{"goal_type":"Traffic","flow_uid":5113,"goal_set":"Video","hold_period":20,"requirements":{"max_latency_s":3.0,"min_throughput_bps":480060.0}},{"goal_type":"Traffic","flow_uid":5114,"goal_set":"Web","hold_period":20,"requirements":{"file_transfer_deadline_s":0.5}},{"goal_type":"Traffic","flow_uid":5115,"goal_set":"Video","hold_period":20,"requirements":{"max_latency_s":3.0,"min_throughput_bps":480060.0}},{"goal_type":"Traffic","flow_uid":5116,"goal_set":"Web","hold_period":20,"requirements":{"file_transfer_deadline_s":0.5}},{"goal_type":"Traffic","flow_uid":5117,"goal_set":"Video","hold_period":20,"requirements":{"max_latency_s":3.0,"min_throughput_bps":480060.0}},{"goal_type":"Traffic","flow_uid":5118,"goal_set":"Web","hold_period":20,"requirements":{"file_transfer_deadline_s":0.5}},{"goal_type":"Traffic","flow_uid":5119,"goal_set":"Files","hold_period":20,"requirements":{"file_transfer_deadline_s":30.0}},{"goal_type":"Traffic","flow_uid":5120,"goal_set":"Video","hold_period":20,"requirements":{"max_latency_s":3.0,"min_throughput_bps":480060.0}},{"goal_type":"Traffic","flow_uid":5121,"goal_set":"Web","hold_period":20,"requirements":{"file_transfer_deadline_s":0.5}},{"goal_type":"Traffic","flow_uid":5122,"goal_set":"Video","hold_period":20,"requirements":{"max_latency_s":3.0,"min_throughput_bps":480060.0}},{"goal_type":"Traffic","flow_uid":5123,"goal_set":"Web","hold_period":20,"requirements":{"file_transfer_deadline_s":0.5}},{"goal_type":"Traffic","flow_uid":5124,"goal_set":"Video","hold_period":20,"requirements":{"max_latency_s":3.0,"min_throughput_bps":480060.0}},{"goal_type":"Traffic","flow_uid":5125,"goal_set":"Web","hold_period":20,"requirements":{"file_transfer_deadline_s":0.5}},{"goal_type":"Traffic","flow_uid":5126,"goal_set":"Video","hold_period":20,"requirements":{"max_latency_s":3.0,"min_throughput_bps":480060.0}},{"goal_type":"Traffic","flow_uid":5127,"goal_set":"Web","hold_period":20,"requirements":{"file_transfer_deadline_s":0.5}},{"goal_type":"Traffic","flow_uid":5128,"goal_set":"Web","hold_period":20,"requirements":{"file_transfer_deadline_s":0.5}},{"goal_type":"Traffic","flow_uid":5129,"goal_set":"Web","hold_period":20,"requirements":{"file_transfer_deadline_s":0.5}},{"goal_type":"Traffic","flow_uid":5130,"goal_set":"Web","hold_period":20,"requirements":{"file_transfer_deadline_s":0.5}},{"goal_type":"Traffic","flow_uid":5131,"goal_set":"Web","hold_period":20,"requirements":{"file_transfer_deadline_s":0.5}},{"goal_type":"Traffic","flow_uid":5132,"goal_set":"Web","hold_period":20,"requirements":{"file_transfer_deadline_s":0.5}},{"goal_type":"Traffic","flow_uid":5133,"goal_set":"Web","hold_period":20,"requirements":{"file_transfer_deadline_s":0.5}},{"goal_type":"Traffic","flow_uid":5134,"goal_set":"Web","hold_period":20,"requirements":{"file_transfer_deadline_s":0.5}},{"goal_type":"Traffic","flow_uid":5135,"goal_set":"Web","hold_period":20,"requirements":{"file_transfer_deadline_s":0.5}},{"goal_type":"Traffic","flow_uid":5136,"goal_set":"Web","hold_period":20,"requirements":{"file_transfer_deadline_s":0.5}},{"goal_type":"Traffic","flow_uid":5137,"goal_set":"Web","hold_period":20,"requirements":{"file_transfer_deadline_s":0.5}},{"goal_type":"Traffic","flow_uid":5138,"goal_set":"Web","hold_period":20,"requirements":{"file_transfer_deadline_s":0.5}},{"goal_type":"Traffic","flow_uid":5139,"goal_set":"Web","hold_period":20,"requirements":{"file_transfer_deadline_s":0.5}},{"goal_type":"Traffic","flow_uid":5140,"goal_set":"Web","hold_period":20,"requirements":{"file_transfer_deadline_s":0.5}},{"goal_type":"Traffic","flow_uid":5141,"goal_set":"Web","hold_period":20,"requirements":{"file_transfer_deadline_s":0.5}},{"goal_type":"Traffic","flow_uid":5142,"goal_set":"Web","hold_period":20,"requirements":{"file_transfer_deadline_s":0.5}},{"goal_type":"Traffic","flow_uid":5143,"goal_set":"Web","hold_period":20,"requirements":{"file_transfer_deadline_s":0.5}},{"goal_type":"Traffic","flow_uid":5144,"goal_set":"Web","hold_period":20,"requirements":{"file_transfer_deadline_s":0.5}}]},{"timestamp":135.0,"scenario_goals":[{"goal_type":"Traffic","flow_uid":5325,"goal_set":"Video","hold_period":20,"requirements":{"max_latency_s":3.0,"min_throughput_bps":480060.0}},{"goal_type":"Traffic","flow_uid":5326,"goal_set":"Web","hold_period":20,"requirements":{"file_transfer_deadline_s":0.5}},{"goal_type":"Traffic","flow_uid":5327,"goal_set":"Video","hold_period":20,"requirements":{"max_latency_s":3.0,"min_throughput_bps":480060.0}},{"goal_type":"Traffic","flow_uid":5328,"goal_set":"Web","hold_period":20,"requirements":{"file_transfer_deadline_s":0.5}},{"goal_type":"Traffic","flow_uid":5329,"goal_set":"Video","hold_period":20,"requirements":{"max_latency_s":3.0,"min_throughput_bps":480060.0}},{"goal_type":"Traffic","flow_uid":5330,"goal_set":"Web","hold_period":20,"requirements":{"file_transfer_deadline_s":0.5}},{"goal_type":"Traffic","flow_uid":5331,"goal_set":"Video","hold_period":20,"requirements":{"max_latency_s":3.0,"min_throughput_bps":480060.0}},{"goal_type":"Traffic","flow_uid":5332,"goal_set":"Web","hold_period":20,"requirements":{"file_transfer_deadline_s":0.5}},{"goal_type":"Traffic","flow_uid":5333,"goal_set":"Video","hold_period":20,"requirements":{"max_latency_s":3.0,"min_throughput_bps":480060.0}},{"goal_type":"Traffic","flow_uid":5334,"goal_set":"Web","hold_period":20,"requirements":{"file_transfer_deadline_s":0.5}},{"goal_type":"Traffic","flow_uid":5335,"goal_set":"Files","hold_period":20,"requirements":{"file_transfer_deadline_s":30.0}},{"goal_type":"Traffic","flow_uid":5336,"goal_set":"Video","hold_period":20,"requirements":{"max_latency_s":3.0,"min_throughput_bps":480060.0}},{"goal_type":"Traffic","flow_uid":5337,"goal_set":"Web","hold_period":20,"requirements":{"file_transfer_deadline_s":0.5}},{"goal_type":"Traffic","flow_uid":5338,"goal_set":"Video","hold_period":20,"requirements":{"max_latency_s":3.0,"min_throughput_bps":480060.0}},{"goal_type":"Traffic","flow_uid":5339,"goal_set":"Web","hold_period":20,"requirements":{"file_transfer_deadline_s":0.5}},{"goal_type":"Traffic","flow_uid":5340,"goal_set":"Video","hold_period":20,"requirements":{"max_latency_s":3.0,"min_throughput_bps":480060.0}},{"goal_type":"Traffic","flow_uid":5341,"goal_set":"Web","hold_period":20,"requirements":{"file_transfer_deadline_s":0.5}},{"goal_type":"Traffic","flow_uid":5342,"goal_set":"Video","hold_period":20,"requirements":{"max_latency_s":3.0,"min_throughput_bps":480060.0}},{"goal_type":"Traffic","flow_uid":5343,"goal_set":"Web","hold_period":20,"requirements":{"file_transfer_deadline_s":0.5}},{"goal_type":"Traffic","flow_uid":5344,"goal_set":"Web","hold_period":20,"requirements":{"file_transfer_deadline_s":0.5}},{"goal_type":"Traffic","flow_uid":5345,"goal_set":"Web","hold_period":20,"requirements":{"file_transfer_deadline_s":0.5}},{"goal_type":"Traffic","flow_uid":5346,"goal_set":"Web","hold_period":20,"requirements":{"file_transfer_deadline_s":0.5}},{"goal_type":"Traffic","flow_uid":5347,"goal_set":"Web","hold_period":20,"requirements":{"file_transfer_deadline_s":0.5}},{"goal_type":"Traffic","flow_uid":5348,"goal_set":"Web","hold_period":20,"requirements":{"file_transfer_deadline_s":0.5}},{"goal_type":"Traffic","flow_uid":5349,"goal_set":"Web","hold_period":20,"requirements":{"file_transfer_deadline_s":0.5}},{"goal_type":"Traffic","flow_uid":5350,"goal_set":"Web","hold_period":20,"requirements":{"file_transfer_deadline_s":0.5}},{"goal_type":"Traffic","flow_uid":5351,"goal_set":"Web","hold_period":20,"requirements":{"file_transfer_deadline_s":0.5}},{"goal_type":"Traffic","flow_uid":5352,"goal_set":"Web","hold_period":20,"requirements":{"file_transfer_deadline_s":0.5}},{"goal_type":"Traffic","flow_uid":5353,"goal_set":"Web","hold_period":20,"requirements":{"file_transfer_deadline_s":0.5}},{"goal_type":"Traffic","flow_uid":5354,"goal_set":"Web","hold_period":20,"requirements":{"file_transfer_deadline_s":0.5}},{"goal_type":"Traffic","flow_uid":5355,"goal_set":"Web","hold_period":20,"requirements":{"file_transfer_deadline_s":0.5}},{"goal_type":"Traffic","flow_uid":5356,"goal_set":"Web","hold_period":20,"requirements":{"file_transfer_deadline_s":0.5}},{"goal_type":"Traffic","flow_uid":5357,"goal_set":"Web","hold_period":20,"requirements":{"file_transfer_deadline_s":0.5}},{"goal_type":"Traffic","flow_uid":5358,"goal_set":"Web","hold_period":20,"requirements":{"file_transfer_deadline_s":0.5}},{"goal_type":"Traffic","flow_uid":5359,"goal_set":"Web","hold_period":20,"requirements":{"file_transfer_deadline_s":0.5}},{"goal_type":"Traffic","flow_uid":5360,"goal_set":"Web","hold_period":20,"requirements":{"file_transfer_deadline_s":0.5}}]},{"timestamp":255.0,"scenario_goals":[{"goal_type":"Traffic","flow_uid":5397,"goal_set":"Video","hold_period":20,"requirements":{"max_latency_s":3.0,"min_throughput_bps":480060.0}},{"goal_type":"Traffic","flow_uid":5398,"goal_set":"Web","hold_period":20,"requirements":{"file_transfer_deadline_s":2.0}},{"goal_type":"Traffic","flow_uid":5399,"goal_set":"Web","hold_period":20,"requirements":{"file_transfer_deadline_s":0.5}},{"goal_type":"Traffic","flow_uid":5400,"goal_set":"Video","hold_period":20,"requirements":{"max_latency_s":3.0,"min_throughput_bps":480060.0}},{"goal_type":"Traffic","flow_uid":5401,"goal_set":"Web","hold_period":20,"requirements":{"file_transfer_deadline_s":2.0}},{"goal_type":"Traffic","flow_uid":5402,"goal_set":"Web","hold_period":20,"requirements":{"file_transfer_deadline_s":0.5}},{"goal_type":"Traffic","flow_uid":5403,"goal_set":"Video","hold_period":20,"requirements":{"max_latency_s":3.0,"min_throughput_bps":480060.0}},{"goal_type":"Traffic","flow_uid":5404,"goal_set":"Web","hold_period":20,"requirements":{"file_transfer_deadline_s":2.0}},{"goal_type":"Traffic","flow_uid":5405,"goal_set":"Web","hold_period":20,"requirements":{"file_transfer_deadline_s":0.5}},{"goal_type":"Traffic","flow_uid":5406,"goal_set":"Video","hold_period":20,"requirements":{"max_latency_s":3.0,"min_throughput_bps":480060.0}},{"goal_type":"Traffic","flow_uid":5407,"goal_set":"Web","hold_period":20,"requirements":{"file_transfer_deadline_s":2.0}},{"goal_type":"Traffic","flow_uid":5408,"goal_set":"Web","hold_period":20,"requirements":{"file_transfer_deadline_s":0.5}},{"goal_type":"Traffic","flow_uid":5409,"goal_set":"Files","hold_period":20,"requirements":{"file_transfer_deadline_s":20.0}},{"goal_type":"Traffic","flow_uid":5410,"goal_set":"Files","hold_period":20,"requirements":{"file_transfer_deadline_s":20.0}},{"goal_type":"Traffic","flow_uid":5411,"goal_set":"Web","hold_period":20,"requirements":{"file_transfer_deadline_s":2.0}},{"goal_type":"Traffic","flow_uid":5412,"goal_set":"Web","hold_period":20,"requirements":{"file_transfer_deadline_s":0.5}},{"goal_type":"Traffic","flow_uid":5413,"goal_set":"Web","hold_period":20,"requirements":{"file_transfer_deadline_s":2.0}},{"goal_type":"Traffic","flow_uid":5414,"goal_set":"Web","hold_period":20,"requirements":{"file_transfer_deadline_s":0.5}},{"goal_type":"Traffic","flow_uid":5415,"goal_set":"Video","hold_period":20,"requirements":{"max_latency_s":3.0,"min_throughput_bps":480060.0}},{"goal_type":"Traffic","flow_uid":5416,"goal_set":"Web","hold_period":20,"requirements":{"file_transfer_deadline_s":0.5}},{"goal_type":"Traffic","flow_uid":5417,"goal_set":"Video","hold_period":20,"requirements":{"max_latency_s":3.0,"min_throughput_bps":480060.0}},{"goal_type":"Traffic","flow_uid":5418,"goal_set":"Web","hold_period":20,"requirements":{"file_transfer_deadline_s":0.5}},{"goal_type":"Traffic","flow_uid":5419,"goal_set":"Web","hold_period":20,"requirements":{"file_transfer_deadline_s":0.5}},{"goal_type":"Traffic","flow_uid":5420,"goal_set":"Web","hold_period":20,"requirements":{"file_transfer_deadline_s":0.5}},{"goal_type":"Traffic","flow_uid":5421,"goal_set":"Web","hold_period":20,"requirements":{"file_transfer_deadline_s":0.5}},{"goal_type":"Traffic","flow_uid":5422,"goal_set":"Web","hold_period":20,"requirements":{"file_transfer_deadline_s":0.5}},{"goal_type":"Traffic","flow_uid":5423,"goal_set":"Web","hold_period":20,"requirements":{"file_transfer_deadline_s":0.5}},{"goal_type":"Traffic","flow_uid":5424,"goal_set":"Web","hold_period":20,"requirements":{"file_transfer_deadline_s":0.5}},{"goal_type":"Traffic","flow_uid":5425,"goal_set":"Web","hold_period":20,"requirements":{"file_transfer_deadline_s":0.5}},{"goal_type":"Traffic","flow_uid":5426,"goal_set":"Web","hold_period":20,"requirements":{"file_transfer_deadline_s":0.5}},{"goal_type":"Traffic","flow_uid":5427,"goal_set":"Web","hold_period":20,"requirements":{"file_transfer_deadline_s":0.5}},{"goal_type":"Traffic","flow_uid":5428,"goal_set":"Web","hold_period":20,"requirements":{"file_transfer_deadline_s":0.5}},{"goal_type":"Traffic","flow_uid":5429,"goal_set":"Web","hold_period":20,"requirements":{"file_transfer_deadline_s":0.5}},{"goal_type":"Traffic","flow_uid":5430,"goal_set":"Web","hold_period":20,"requirements":{"file_transfer_deadline_s":0.5}},{"goal_type":"Traffic","flow_uid":5431,"goal_set":"Web","hold_period":20,"requirements":{"file_transfer_deadline_s":0.5}},{"goal_type":"Traffic","flow_uid":5432,"goal_set":"Web","hold_period":20,"requirements":{"file_transfer_deadline_s":0.5}}]},{"timestamp":375.0,"scenario_goals":[{"goal_type":"Traffic","flow_uid":5541,"goal_set":"Video","hold_period":20,"requirements":{"max_latency_s":3.0,"min_throughput_bps":1536314.5999999999}},{"goal_type":"Traffic","flow_uid":5542,"goal_set":"Web","hold_period":20,"requirements":{"file_transfer_deadline_s":2.0}},{"goal_type":"Traffic","flow_uid":5543,"goal_set":"Web","hold_period":20,"requirements":{"file_transfer_deadline_s":0.5}},{"goal_type":"Traffic","flow_uid":5544,"goal_set":"Video","hold_period":20,"requirements":{"max_latency_s":3.0,"min_throughput_bps":1536314.5999999999}},{"goal_type":"Traffic","flow_uid":5545,"goal_set":"Web","hold_period":20,"requirements":{"file_transfer_deadline_s":2.0}},{"goal_type":"Traffic","flow_uid":5546,"goal_set":"Web","hold_period":20,"requirements":{"file_transfer_deadline_s":0.5}},{"goal_type":"Traffic","flow_uid":5547,"goal_set":"Video","hold_period":20,"requirements":{"max_latency_s":3.0,"min_throughput_bps":1536314.5999999999}},{"goal_type":"Traffic","flow_uid":5548,"goal_set":"Web","hold_period":20,"requirements":{"file_transfer_deadline_s":2.0}},{"goal_type":"Traffic","flow_uid":5549,"goal_set":"Web","hold_period":20,"requirements":{"file_transfer_deadline_s":0.5}},{"goal_type":"Traffic","flow_uid":5550,"goal_set":"Web","hold_period":20,"requirements":{"file_transfer_deadline_s":2.0}},{"goal_type":"Traffic","flow_uid":5551,"goal_set":"Web","hold_period":20,"requirements":{"file_transfer_deadline_s":0.5}},{"goal_type":"Traffic","flow_uid":5552,"goal_set":"Video","hold_period":20,"requirements":{"max_latency_s":3.0,"min_throughput_bps":480060.0}},{"goal_type":"Traffic","flow_uid":5553,"goal_set":"Web","hold_period":20,"requirements":{"file_transfer_deadline_s":0.5}},{"goal_type":"Traffic","flow_uid":5554,"goal_set":"Files","hold_period":20,"requirements":{"file_transfer_deadline_s":16.0}},{"goal_type":"Traffic","flow_uid":5555,"goal_set":"Files","hold_period":20,"requirements":{"file_transfer_deadline_s":20.0}},{"goal_type":"Traffic","flow_uid":5556,"goal_set":"Web","hold_period":20,"requirements":{"file_transfer_deadline_s":2.0}},{"goal_type":"Traffic","flow_uid":5557,"goal_set":"Web","hold_period":20,"requirements":{"file_transfer_deadline_s":0.5}},{"goal_type":"Traffic","flow_uid":5558,"goal_set":"Video","hold_period":20,"requirements":{"max_latency_s":3.0,"min_throughput_bps":480060.0}},{"goal_type":"Traffic","flow_uid":5559,"goal_set":"Web","hold_period":20,"requirements":{"file_transfer_deadline_s":0.5}},{"goal_type":"Traffic","flow_uid":5560,"goal_set":"Files","hold_period":20,"requirements":{"file_transfer_deadline_s":16.0}},{"goal_type":"Traffic","flow_uid":5561,"goal_set":"Files","hold_period":20,"requirements":{"file_transfer_deadline_s":20.0}},{"goal_type":"Traffic","flow_uid":5562,"goal_set":"Video","hold_period":20,"requirements":{"max_latency_s":3.0,"min_throughput_bps":480060.0}},{"goal_type":"Traffic","flow_uid":5563,"goal_set":"Web","hold_period":20,"requirements":{"file_transfer_deadline_s":2.0}},{"goal_type":"Traffic","flow_uid":5564,"goal_set":"Web","hold_period":20,"requirements":{"file_transfer_deadline_s":0.5}},{"goal_type":"Traffic","flow_uid":5565,"goal_set":"Video","hold_period":20,"requirements":{"max_latency_s":3.0,"min_throughput_bps":480060.0}},{"goal_type":"Traffic","flow_uid":5566,"goal_set":"Web","hold_period":20,"requirements":{"file_transfer_deadline_s":2.0}},{"goal_type":"Traffic","flow_uid":5567,"goal_set":"Web","hold_period":20,"requirements":{"file_transfer_deadline_s":0.5}},{"goal_type":"Traffic","flow_uid":5568,"goal_set":"Files","hold_period":20,"requirements":{"file_transfer_deadline_s":20.0}},{"goal_type":"Traffic","flow_uid":5569,"goal_set":"Files","hold_period":20,"requirements":{"file_transfer_deadline_s":20.0}},{"goal_type":"Traffic","flow_uid":5570,"goal_set":"Web","hold_period":20,"requirements":{"file_transfer_deadline_s":0.5}},{"goal_type":"Traffic","flow_uid":5571,"goal_set":"Web","hold_period":20,"requirements":{"file_transfer_deadline_s":0.5}},{"goal_type":"Traffic","flow_uid":5572,"goal_set":"Web","hold_period":20,"requirements":{"file_transfer_deadline_s":0.5}},{"goal_type":"Traffic","flow_uid":5573,"goal_set":"Web","hold_period":20,"requirements":{"file_transfer_deadline_s":0.5}},{"goal_type":"Traffic","flow_uid":5574,"goal_set":"Web","hold_period":20,"requirements":{"file_transfer_deadline_s":0.5}},{"goal_type":"Traffic","flow_uid":5575,"goal_set":"Web","hold_period":20,"requirements":{"file_transfer_deadline_s":0.5}},{"goal_type":"Traffic","flow_uid":5576,"goal_set":"Web","hold_period":20,"requirements":{"file_transfer_deadline_s":0.5}}]},{"timestamp":495.0,"scenario_goals":[{"goal_type":"Traffic","flow_uid":5793,"goal_set":"Video","hold_period":20,"requirements":{"max_latency_s":3.0,"min_throughput_bps":480060.0}},{"goal_type":"Traffic","flow_uid":5794,"goal_set":"Web","hold_period":20,"requirements":{"file_transfer_deadline_s":0.5}},{"goal_type":"Traffic","flow_uid":5795,"goal_set":"Video","hold_period":20,"requirements":{"max_latency_s":3.0,"min_throughput_bps":480060.0}},{"goal_type":"Traffic","flow_uid":5796,"goal_set":"Web","hold_period":20,"requirements":{"file_transfer_deadline_s":0.5}},{"goal_type":"Traffic","flow_uid":5797,"goal_set":"Video","hold_period":20,"requirements":{"max_latency_s":3.0,"min_throughput_bps":480060.0}},{"goal_type":"Traffic","flow_uid":5798,"goal_set":"Web","hold_period":20,"requirements":{"file_transfer_deadline_s":0.5}},{"goal_type":"Traffic","flow_uid":5799,"goal_set":"Video","hold_period":20,"requirements":{"max_latency_s":3.0,"min_throughput_bps":480060.0}},{"goal_type":"Traffic","flow_uid":5800,"goal_set":"Web","hold_period":20,"requirements":{"file_transfer_deadline_s":0.5}},{"goal_type":"Traffic","flow_uid":5801,"goal_set":"Video","hold_period":20,"requirements":{"max_latency_s":3.0,"min_throughput_bps":480060.0}},{"goal_type":"Traffic","flow_uid":5802,"goal_set":"Web","hold_period":20,"requirements":{"file_transfer_deadline_s":0.5}},{"goal_type":"Traffic","flow_uid":5803,"goal_set":"Files","hold_period":20,"requirements":{"file_transfer_deadline_s":30.0}},{"goal_type":"Traffic","flow_uid":5804,"goal_set":"Video","hold_period":20,"requirements":{"max_latency_s":3.0,"min_throughput_bps":480060.0}},{"goal_type":"Traffic","flow_uid":5805,"goal_set":"Web","hold_period":20,"requirements":{"file_transfer_deadline_s":0.5}},{"goal_type":"Traffic","flow_uid":5806,"goal_set":"Video","hold_period":20,"requirements":{"max_latency_s":3.0,"min_throughput_bps":480060.0}},{"goal_type":"Traffic","flow_uid":5807,"goal_set":"Web","hold_period":20,"requirements":{"file_transfer_deadline_s":0.5}},{"goal_type":"Traffic","flow_uid":5808,"goal_set":"Video","hold_period":20,"requirements":{"max_latency_s":3.0,"min_throughput_bps":480060.0}},{"goal_type":"Traffic","flow_uid":5809,"goal_set":"Web","hold_period":20,"requirements":{"file_transfer_deadline_s":0.5}},{"goal_type":"Traffic","flow_uid":5810,"goal_set":"Video","hold_period":20,"requirements":{"max_latency_s":3.0,"min_throughput_bps":480060.0}},{"goal_type":"Traffic","flow_uid":5811,"goal_set":"Web","hold_period":20,"requirements":{"file_transfer_deadline_s":0.5}},{"goal_type":"Traffic","flow_uid":5812,"goal_set":"Web","hold_period":20,"requirements":{"file_transfer_deadline_s":0.5}},{"goal_type":"Traffic","flow_uid":5813,"goal_set":"Web","hold_period":20,"requirements":{"file_transfer_deadline_s":0.5}},{"goal_type":"Traffic","flow_uid":5814,"goal_set":"Web","hold_period":20,"requirements":{"file_transfer_deadline_s":0.5}},{"goal_type":"Traffic","flow_uid":5815,"goal_set":"Web","hold_period":20,"requirements":{"file_transfer_deadline_s":0.5}},{"goal_type":"Traffic","flow_uid":5816,"goal_set":"Web","hold_period":20,"requirements":{"file_transfer_deadline_s":0.5}},{"goal_type":"Traffic","flow_uid":5817,"goal_set":"Web","hold_period":20,"requirements":{"file_transfer_deadline_s":0.5}},{"goal_type":"Traffic","flow_uid":5818,"goal_set":"Web","hold_period":20,"requirements":{"file_transfer_deadline_s":0.5}},{"goal_type":"Traffic","flow_uid":5819,"goal_set":"Web","hold_period":20,"requirements":{"file_transfer_deadline_s":0.5}},{"goal_type":"Traffic","flow_uid":5820,"goal_set":"Web","hold_period":20,"requirements":{"file_transfer_deadline_s":0.5}},{"goal_type":"Traffic","flow_uid":5821,"goal_set":"Web","hold_period":20,"requirements":{"file_transfer_deadline_s":0.5}},{"goal_type":"Traffic","flow_uid":5822,"goal_set":"Web","hold_period":20,"requirements":{"file_transfer_deadline_s":0.5}},{"goal_type":"Traffic","flow_uid":5823,"goal_set":"Web","hold_period":20,"requirements":{"file_transfer_deadline_s":0.5}},{"goal_type":"Traffic","flow_uid":5824,"goal_set":"Web","hold_period":20,"requirements":{"file_transfer_deadline_s":0.5}},{"goal_type":"Traffic","flow_uid":5825,"goal_set":"Web","hold_period":20,"requirements":{"file_transfer_deadline_s":0.5}},{"goal_type":"Traffic","flow_uid":5826,"goal_set":"Web","hold_period":20,"requirements":{"file_transfer_deadline_s":0.5}},{"goal_type":"Traffic","flow_uid":5827,"goal_set":"Web","hold_period":20,"requirements":{"file_transfer_deadline_s":0.5}},{"goal_type":"Traffic","flow_uid":5828,"goal_set":"Web","hold_period":20,"requirements":{"file_transfer_deadline_s":0.5}}]},{"timestamp":615.0,"scenario_goals":[{"goal_type":"Traffic","flow_uid":6045,"goal_set":"Files","hold_period":20,"requirements":{"file_transfer_deadline_s":30.0}},{"goal_type":"Traffic","flow_uid":6046,"goal_set":"Video","hold_period":20,"requirements":{"max_latency_s":3.0,"min_throughput_bps":480060.0}},{"goal_type":"Traffic","flow_uid":6047,"goal_set":"Web","hold_period":20,"requirements":{"file_transfer_deadline_s":0.5}},{"goal_type":"Traffic","flow_uid":6048,"goal_set":"Video","hold_period":20,"requirements":{"max_latency_s":3.0,"min_throughput_bps":480060.0}},{"goal_type":"Traffic","flow_uid":6049,"goal_set":"Web","hold_period":20,"requirements":{"file_transfer_deadline_s":0.5}},{"goal_type":"Traffic","flow_uid":6050,"goal_set":"Video","hold_period":20,"requirements":{"max_latency_s":3.0,"min_throughput_bps":480060.0}},{"goal_type":"Traffic","flow_uid":6051,"goal_set":"Web","hold_period":20,"requirements":{"file_transfer_deadline_s":0.5}},{"goal_type":"Traffic","flow_uid":6052,"goal_set":"Web","hold_period":20,"requirements":{"file_transfer_deadline_s":2.0}},{"goal_type":"Traffic","flow_uid":6053,"goal_set":"Web","hold_period":20,"requirements":{"file_transfer_deadline_s":0.5}},{"goal_type":"Traffic","flow_uid":6054,"goal_set":"Web","hold_period":20,"requirements":{"file_transfer_deadline_s":2.0}},{"goal_type":"Traffic","flow_uid":6055,"goal_set":"Web","hold_period":20,"requirements":{"file_transfer_deadline_s":0.5}},{"goal_type":"Traffic","flow_uid":6056,"goal_set":"Video","hold_period":20,"requirements":{"max_latency_s":3.0,"min_throughput_bps":480060.0}},{"goal_type":"Traffic","flow_uid":6057,"goal_set":"Web","hold_period":20,"requirements":{"file_transfer_deadline_s":0.5}},{"goal_type":"Traffic","flow_uid":6058,"goal_set":"Video","hold_period":20,"requirements":{"max_latency_s":3.0,"min_throughput_bps":480060.0}},{"goal_type":"Traffic","flow_uid":6059,"goal_set":"Web","hold_period":20,"requirements":{"file_transfer_deadline_s":0.5}},{"goal_type":"Traffic","flow_uid":6060,"goal_set":"Video","hold_period":20,"requirements":{"max_latency_s":3.0,"min_throughput_bps":480060.0}},{"goal_type":"Traffic","flow_uid":6061,"goal_set":"Web","hold_period":20,"requirements":{"file_transfer_deadline_s":0.5}},{"goal_type":"Traffic","flow_uid":6062,"goal_set":"Video","hold_period":20,"requirements":{"max_latency_s":3.0,"min_throughput_bps":480060.0}},{"goal_type":"Traffic","flow_uid":6063,"goal_set":"Web","hold_period":20,"requirements":{"file_transfer_deadline_s":0.5}},{"goal_type":"Traffic","flow_uid":6064,"goal_set":"Web","hold_period":20,"requirements":{"file_transfer_deadline_s":0.5}},{"goal_type":"Traffic","flow_uid":6065,"goal_set":"Web","hold_period":20,"requirements":{"file_transfer_deadline_s":0.5}},{"goal_type":"Traffic","flow_uid":6066,"goal_set":"Web","hold_period":20,"requirements":{"file_transfer_deadline_s":0.5}},{"goal_type":"Traffic","flow_uid":6067,"goal_set":"Web","hold_period":20,"requirements":{"file_transfer_deadline_s":0.5}},{"goal_type":"Traffic","flow_uid":6068,"goal_set":"Web","hold_period":20,"requirements":{"file_transfer_deadline_s":0.5}},{"goal_type":"Traffic","flow_uid":6069,"goal_set":"Web","hold_period":20,"requirements":{"file_transfer_deadline_s":0.5}},{"goal_type":"Traffic","flow_uid":6070,"goal_set":"Web","hold_period":20,"requirements":{"file_transfer_deadline_s":0.5}},{"goal_type":"Traffic","flow_uid":6071,"goal_set":"Web","hold_period":20,"requirements":{"file_transfer_deadline_s":0.5}},{"goal_type":"Traffic","flow_uid":6072,"goal_set":"Web","hold_period":20,"requirements":{"file_transfer_deadline_s":0.5}},{"goal_type":"Traffic","flow_uid":6073,"goal_set":"Web","hold_period":20,"requirements":{"file_transfer_deadline_s":0.5}},{"goal_type":"Traffic","flow_uid":6074,"goal_set":"Web","hold_period":20,"requirements":{"file_transfer_deadline_s":0.5}},{"goal_type":"Traffic","flow_uid":6075,"goal_set":"Web","hold_period":20,"requirements":{"file_transfer_deadline_s":0.5}},{"goal_type":"Traffic","flow_uid":6076,"goal_set":"Web","hold_period":20,"requirements":{"file_transfer_deadline_s":0.5}},{"goal_type":"Traffic","flow_uid":6077,"goal_set":"Web","hold_period":20,"requirements":{"file_transfer_deadline_s":0.5}},{"goal_type":"Traffic","flow_uid":6078,"goal_set":"Web","hold_period":20,"requirements":{"file_transfer_deadline_s":0.5}},{"goal_type":"Traffic","flow_uid":6079,"goal_set":"Web","hold_period":20,"requirements":{"file_transfer_deadline_s":0.5}},{"goal_type":"Traffic","flow_uid":6080,"goal_set":"Web","hold_period":20,"requirements":{"file_transfer_deadline_s":0.5}}]},{"timestamp":735.0,"scenario_goals":[{"goal_type":"Traffic","flow_uid":6225,"goal_set":"Files","hold_period":20,"requirements":{"file_transfer_deadline_s":30.0}},{"goal_type":"Traffic","flow_uid":6226,"goal_set":"Video","hold_period":20,"requirements":{"max_latency_s":3.0,"min_throughput_bps":480060.0}},{"goal_type":"Traffic","flow_uid":6227,"goal_set":"Web","hold_period":20,"requirements":{"file_transfer_deadline_s":0.5}},{"goal_type":"Traffic","flow_uid":6228,"goal_set":"Video","hold_period":20,"requirements":{"max_latency_s":3.0,"min_throughput_bps":480060.0}},{"goal_type":"Traffic","flow_uid":6229,"goal_set":"Web","hold_period":20,"requirements":{"file_transfer_deadline_s":0.5}},{"goal_type":"Traffic","flow_uid":6230,"goal_set":"Video","hold_period":20,"requirements":{"max_latency_s":3.0,"min_throughput_bps":480060.0}},{"goal_type":"Traffic","flow_uid":6231,"goal_set":"Web","hold_period":20,"requirements":{"file_transfer_deadline_s":0.5}},{"goal_type":"Traffic","flow_uid":6232,"goal_set":"Web","hold_period":20,"requirements":{"file_transfer_deadline_s":2.0}},{"goal_type":"Traffic","flow_uid":6233,"goal_set":"Web","hold_period":20,"requirements":{"file_transfer_deadline_s":0.5}},{"goal_type":"Traffic","flow_uid":6234,"goal_set":"Web","hold_period":20,"requirements":{"file_transfer_deadline_s":2.0}},{"goal_type":"Traffic","flow_uid":6235,"goal_set":"Web","hold_period":20,"requirements":{"file_transfer_deadline_s":0.5}},{"goal_type":"Traffic","flow_uid":6236,"goal_set":"Video","hold_period":20,"requirements":{"max_latency_s":3.0,"min_throughput_bps":480060.0}},{"goal_type":"Traffic","flow_uid":6237,"goal_set":"Web","hold_period":20,"requirements":{"file_transfer_deadline_s":0.5}},{"goal_type":"Traffic","flow_uid":6238,"goal_set":"Video","hold_period":20,"requirements":{"max_latency_s":3.0,"min_throughput_bps":480060.0}},{"goal_type":"Traffic","flow_uid":6239,"goal_set":"Web","hold_period":20,"requirements":{"file_transfer_deadline_s":0.5}},{"goal_type":"Traffic","flow_uid":6240,"goal_set":"Video","hold_period":20,"requirements":{"max_latency_s":3.0,"min_throughput_bps":480060.0}},{"goal_type":"Traffic","flow_uid":6241,"goal_set":"Web","hold_period":20,"requirements":{"file_transfer_deadline_s":0.5}},{"goal_type":"Traffic","flow_uid":6242,"goal_set":"Video","hold_period":20,"requirements":{"max_latency_s":3.0,"min_throughput_bps":480060.0}},{"goal_type":"Traffic","flow_uid":6243,"goal_set":"Web","hold_period":20,"requirements":{"file_transfer_deadline_s":0.5}},{"goal_type":"Traffic","flow_uid":6244,"goal_set":"Web","hold_period":20,"requirements":{"file_transfer_deadline_s":0.5}},{"goal_type":"Traffic","flow_uid":6245,"goal_set":"Web","hold_period":20,"requirements":{"file_transfer_deadline_s":0.5}},{"goal_type":"Traffic","flow_uid":6246,"goal_set":"Web","hold_period":20,"requirements":{"file_transfer_deadline_s":0.5}},{"goal_type":"Traffic","flow_uid":6247,"goal_set":"Web","hold_period":20,"requirements":{"file_transfer_deadline_s":0.5}},{"goal_type":"Traffic","flow_uid":6248,"goal_set":"Web","hold_period":20,"requirements":{"file_transfer_deadline_s":0.5}},{"goal_type":"Traffic","flow_uid":6249,"goal_set":"Web","hold_period":20,"requirements":{"file_transfer_deadline_s":0.5}},{"goal_type":"Traffic","flow_uid":6250,"goal_set":"Web","hold_period":20,"requirements":{"file_transfer_deadline_s":0.5}},{"goal_type":"Traffic","flow_uid":6251,"goal_set":"Web","hold_period":20,"requirements":{"file_transfer_deadline_s":0.5}},{"goal_type":"Traffic","flow_uid":6252,"goal_set":"Web","hold_period":20,"requirements":{"file_transfer_deadline_s":0.5}},{"goal_type":"Traffic","flow_uid":6253,"goal_set":"Web","hold_period":20,"requirements":{"file_transfer_deadline_s":0.5}},{"goal_type":"Traffic","flow_uid":6254,"goal_set":"Web","hold_period":20,"requirements":{"file_transfer_deadline_s":0.5}},{"goal_type":"Traffic","flow_uid":6255,"goal_set":"Web","hold_period":20,"requirements":{"file_transfer_deadline_s":0.5}},{"goal_type":"Traffic","flow_uid":6256,"goal_set":"Web","hold_period":20,"requirements":{"file_transfer_deadline_s":0.5}},{"goal_type":"Traffic","flow_uid":6257,"goal_set":"Web","hold_period":20,"requirements":{"file_transfer_deadline_s":0.5}},{"goal_type":"Traffic","flow_uid":6258,"goal_set":"Web","hold_period":20,"requirements":{"file_transfer_deadline_s":0.5}},{"goal_type":"Traffic","flow_uid":6259,"goal_set":"Web","hold_period":20,"requirements":{"file_transfer_deadline_s":0.5}},{"goal_type":"Traffic","flow_uid":6260,"goal_set":"Web","hold_period":20,"requirements":{"file_transfer_deadline_s":0.5}}]},{"timestamp":855.0,"scenario_goals":[{"goal_type":"Traffic","flow_uid":6297,"goal_set":"Video","hold_period":20,"requirements":{"max_latency_s":3.0,"min_throughput_bps":1536314.5999999999}},{"goal_type":"Traffic","flow_uid":6298,"goal_set":"Video","hold_period":20,"requirements":{"max_latency_s":3.0,"min_throughput_bps":1536314.5999999999}},{"goal_type":"Traffic","flow_uid":6299,"goal_set":"Web","hold_period":20,"requirements":{"file_transfer_deadline_s":2.0}},{"goal_type":"Traffic","flow_uid":6300,"goal_set":"Web","hold_period":20,"requirements":{"file_transfer_deadline_s":0.5}},{"goal_type":"Traffic","flow_uid":6301,"goal_set":"Video","hold_period":20,"requirements":{"max_latency_s":3.0,"min_throughput_bps":480060.0}},{"goal_type":"Traffic","flow_uid":6302,"goal_set":"Web","hold_period":20,"requirements":{"file_transfer_deadline_s":0.5}},{"goal_type":"Traffic","flow_uid":6303,"goal_set":"Web","hold_period":20,"requirements":{"file_transfer_deadline_s":2.0}},{"goal_type":"Traffic","flow_uid":6304,"goal_set":"Web","hold_period":20,"requirements":{"file_transfer_deadline_s":0.5}},{"goal_type":"Traffic","flow_uid":6305,"goal_set":"Video","hold_period":20,"requirements":{"max_latency_s":3.0,"min_throughput_bps":480060.0}},{"goal_type":"Traffic","flow_uid":6306,"goal_set":"Web","hold_period":20,"requirements":{"file_transfer_deadline_s":0.5}},{"goal_type":"Traffic","flow_uid":6307,"goal_set":"Files","hold_period":20,"requirements":{"file_transfer_deadline_s":14.0}},{"goal_type":"Traffic","flow_uid":6308,"goal_set":"Files","hold_period":20,"requirements":{"file_transfer_deadline_s":14.0}},{"goal_type":"Traffic","flow_uid":6309,"goal_set":"Web","hold_period":20,"requirements":{"file_transfer_deadline_s":2.0}},{"goal_type":"Traffic","flow_uid":6310,"goal_set":"Web","hold_period":20,"requirements":{"file_transfer_deadline_s":0.5}},{"goal_type":"Traffic","flow_uid":6311,"goal_set":"Web","hold_period":20,"requirements":{"file_transfer_deadline_s":2.0}},{"goal_type":"Traffic","flow_uid":6312,"goal_set":"Web","hold_period":20,"requirements":{"file_transfer_deadline_s":0.5}},{"goal_type":"Traffic","flow_uid":6313,"goal_set":"Files","hold_period":20,"requirements":{"file_transfer_deadline_s":30.0}},{"goal_type":"Traffic","flow_uid":6314,"goal_set":"Files","hold_period":20,"requirements":{"file_transfer_deadline_s":30.0}},{"goal_type":"Traffic","flow_uid":6315,"goal_set":"Web","hold_period":20,"requirements":{"file_transfer_deadline_s":0.5}},{"goal_type":"Traffic","flow_uid":6316,"goal_set":"Web","hold_period":20,"requirements":{"file_transfer_deadline_s":0.5}},{"goal_type":"Traffic","flow_uid":6317,"goal_set":"Web","hold_period":20,"requirements":{"file_transfer_deadline_s":0.5}},{"goal_type":"Traffic","flow_uid":6318,"goal_set":"Web","hold_period":20,"requirements":{"file_transfer_deadline_s":0.5}},{"goal_type":"Traffic","flow_uid":6319,"goal_set":"Web","hold_period":20,"requirements":{"file_transfer_deadline_s":0.5}},{"goal_type":"Traffic","flow_uid":6320,"goal_set":"Web","hold_period":20,"requirements":{"file_transfer_deadline_s":0.5}},{"goal_type":"Traffic","flow_uid":6321,"goal_set":"Web","hold_period":20,"requirements":{"file_transfer_deadline_s":0.5}},{"goal_type":"Traffic","flow_uid":6322,"goal_set":"Web","hold_period":20,"requirements":{"file_transfer_deadline_s":0.5}},{"goal_type":"Traffic","flow_uid":6323,"goal_set":"Web","hold_period":20,"requirements":{"file_transfer_deadline_s":0.5}},{"goal_type":"Traffic","flow_uid":6324,"goal_set":"Web","hold_period":20,"requirements":{"file_transfer_deadline_s":0.5}},{"goal_type":"Traffic","flow_uid":6325,"goal_set":"Web","hold_period":20,"requirements":{"file_transfer_deadline_s":0.5}},{"goal_type":"Traffic","flow_uid":6326,"goal_set":"Web","hold_period":20,"requirements":{"file_transfer_deadline_s":0.5}},{"goal_type":"Traffic","flow_uid":6327,"goal_set":"Web","hold_period":20,"requirements":{"file_transfer_deadline_s":0.5}},{"goal_type":"Traffic","flow_uid":6328,"goal_set":"Web","hold_period":20,"requirements":{"file_transfer_deadline_s":0.5}},{"goal_type":"Traffic","flow_uid":6329,"goal_set":"Web","hold_period":20,"requirements":{"file_transfer_deadline_s":0.5}},{"goal_type":"Traffic","flow_uid":6330,"goal_set":"Web","hold_period":20,"requirements":{"file_transfer_deadline_s":0.5}},{"goal_type":"Traffic","flow_uid":6331,"goal_set":"Web","hold_period":20,"requirements":{"file_transfer_deadline_s":0.5}},{"goal_type":"Traffic","flow_uid":6332,"goal_set":"Web","hold_period":20,"requirements":{"file_transfer_deadline_s":0.5}}]},{"timestamp":975.0,"scenario_goals":[{"goal_type":"Traffic","flow_uid":6441,"goal_set":"Video","hold_period":20,"requirements":{"max_latency_s":3.0,"min_throughput_bps":1536314.5999999999}},{"goal_type":"Traffic","flow_uid":6442,"goal_set":"Web","hold_period":20,"requirements":{"file_transfer_deadline_s":2.0}},{"goal_type":"Traffic","flow_uid":6443,"goal_set":"Web","hold_period":20,"requirements":{"file_transfer_deadline_s":0.5}},{"goal_type":"Traffic","flow_uid":6444,"goal_set":"Files","hold_period":20,"requirements":{"file_transfer_deadline_s":30.0}},{"goal_type":"Traffic","flow_uid":6445,"goal_set":"Video","hold_period":20,"requirements":{"max_latency_s":3.0,"min_throughput_bps":1536314.5999999999}},{"goal_type":"Traffic","flow_uid":6446,"goal_set":"Web","hold_period":20,"requirements":{"file_transfer_deadline_s":2.0}},{"goal_type":"Traffic","flow_uid":6447,"goal_set":"Web","hold_period":20,"requirements":{"file_transfer_deadline_s":0.5}},{"goal_type":"Traffic","flow_uid":6448,"goal_set":"Files","hold_period":20,"requirements":{"file_transfer_deadline_s":30.0}},{"goal_type":"Traffic","flow_uid":6449,"goal_set":"Web","hold_period":20,"requirements":{"file_transfer_deadline_s":2.0}},{"goal_type":"Traffic","flow_uid":6450,"goal_set":"Web","hold_period":20,"requirements":{"file_transfer_deadline_s":0.5}},{"goal_type":"Traffic","flow_uid":6451,"goal_set":"Video","hold_period":20,"requirements":{"max_latency_s":3.0,"min_throughput_bps":480060.0}},{"goal_type":"Traffic","flow_uid":6452,"goal_set":"Web","hold_period":20,"requirements":{"file_transfer_deadline_s":0.5}},{"goal_type":"Traffic","flow_uid":6453,"goal_set":"Files","hold_period":20,"requirements":{"file_transfer_deadline_s":16.0}},{"goal_type":"Traffic","flow_uid":6454,"goal_set":"Files","hold_period":20,"requirements":{"file_transfer_deadline_s":20.0}},{"goal_type":"Traffic","flow_uid":6455,"goal_set":"Web","hold_period":20,"requirements":{"file_transfer_deadline_s":2.0}},{"goal_type":"Traffic","flow_uid":6456,"goal_set":"Web","hold_period":20,"requirements":{"file_transfer_deadline_s":0.5}},{"goal_type":"Traffic","flow_uid":6457,"goal_set":"Video","hold_period":20,"requirements":{"max_latency_s":3.0,"min_throughput_bps":480060.0}},{"goal_type":"Traffic","flow_uid":6458,"goal_set":"Web","hold_period":20,"requirements":{"file_transfer_deadline_s":0.5}},{"goal_type":"Traffic","flow_uid":6459,"goal_set":"Files","hold_period":20,"requirements":{"file_transfer_deadline_s":16.0}},{"goal_type":"Traffic","flow_uid":6460,"goal_set":"Files","hold_period":20,"requirements":{"file_transfer_deadline_s":20.0}},{"goal_type":"Traffic","flow_uid":6461,"goal_set":"Web","hold_period":20,"requirements":{"file_transfer_deadline_s":2.0}},{"goal_type":"Traffic","flow_uid":6462,"goal_set":"Web","hold_period":20,"requirements":{"file_transfer_deadline_s":0.5}},{"goal_type":"Traffic","flow_uid":6463,"goal_set":"Video","hold_period":20,"requirements":{"max_latency_s":3.0,"min_throughput_bps":480060.0}},{"goal_type":"Traffic","flow_uid":6464,"goal_set":"Web","hold_period":20,"requirements":{"file_transfer_deadline_s":0.5}},{"goal_type":"Traffic","flow_uid":6465,"goal_set":"Files","hold_period":20,"requirements":{"file_transfer_deadline_s":16.0}},{"goal_type":"Traffic","flow_uid":6466,"goal_set":"Files","hold_period":20,"requirements":{"file_transfer_deadline_s":20.0}},{"goal_type":"Traffic","flow_uid":6467,"goal_set":"Video","hold_period":20,"requirements":{"max_latency_s":3.0,"min_throughput_bps":480060.0}},{"goal_type":"Traffic","flow_uid":6468,"goal_set":"Web","hold_period":20,"requirements":{"file_transfer_deadline_s":0.5}},{"goal_type":"Traffic","flow_uid":6469,"goal_set":"Web","hold_period":20,"requirements":{"file_transfer_deadline_s":2.0}},{"goal_type":"Traffic","flow_uid":6470,"goal_set":"Web","hold_period":20,"requirements":{"file_transfer_deadline_s":0.5}},{"goal_type":"Traffic","flow_uid":6471,"goal_set":"Video","hold_period":20,"requirements":{"max_latency_s":3.0,"min_throughput_bps":480060.0}},{"goal_type":"Traffic","flow_uid":6472,"goal_set":"Web","hold_period":20,"requirements":{"file_transfer_deadline_s":0.5}},{"goal_type":"Traffic","flow_uid":6473,"goal_set":"Web","hold_period":20,"requirements":{"file_transfer_deadline_s":2.0}},{"goal_type":"Traffic","flow_uid":6474,"goal_set":"Web","hold_period":20,"requirements":{"file_transfer_deadline_s":0.5}},{"goal_type":"Traffic","flow_uid":6475,"goal_set":"Files","hold_period":20,"requirements":{"file_transfer_deadline_s":14.0}},{"goal_type":"Traffic","flow_uid":6476,"goal_set":"Files","hold_period":20,"requirements":{"file_transfer_deadline_s":14.0}}]},{"timestamp":1095.0,"scenario_goals":[{"goal_type":"Traffic","flow_uid":6693,"goal_set":"Files","hold_period":20,"requirements":{"file_transfer_deadline_s":30.0}},{"goal_type":"Traffic","flow_uid":6694,"goal_set":"Video","hold_period":20,"requirements":{"max_latency_s":3.0,"min_throughput_bps":480060.0}},{"goal_type":"Traffic","flow_uid":6695,"goal_set":"Web","hold_period":20,"requirements":{"file_transfer_deadline_s":0.5}},{"goal_type":"Traffic","flow_uid":6696,"goal_set":"Video","hold_period":20,"requirements":{"max_latency_s":3.0,"min_throughput_bps":480060.0}},{"goal_type":"Traffic","flow_uid":6697,"goal_set":"Web","hold_period":20,"requirements":{"file_transfer_deadline_s":0.5}},{"goal_type":"Traffic","flow_uid":6698,"goal_set":"Video","hold_period":20,"requirements":{"max_latency_s":3.0,"min_throughput_bps":480060.0}},{"goal_type":"Traffic","flow_uid":6699,"goal_set":"Web","hold_period":20,"requirements":{"file_transfer_deadline_s":0.5}},{"goal_type":"Traffic","flow_uid":6700,"goal_set":"Web","hold_period":20,"requirements":{"file_transfer_deadline_s":2.0}},{"goal_type":"Traffic","flow_uid":6701,"goal_set":"Web","hold_period":20,"requirements":{"file_transfer_deadline_s":0.5}},{"goal_type":"Traffic","flow_uid":6702,"goal_set":"Web","hold_period":20,"requirements":{"file_transfer_deadline_s":2.0}},{"goal_type":"Traffic","flow_uid":6703,"goal_set":"Web","hold_period":20,"requirements":{"file_transfer_deadline_s":0.5}},{"goal_type":"Traffic","flow_uid":6704,"goal_set":"Video","hold_period":20,"requirements":{"max_latency_s":3.0,"min_throughput_bps":480060.0}},{"goal_type":"Traffic","flow_uid":6705,"goal_set":"Web","hold_period":20,"requirements":{"file_transfer_deadline_s":0.5}},{"goal_type":"Traffic","flow_uid":6706,"goal_set":"Video","hold_period":20,"requirements":{"max_latency_s":3.0,"min_throughput_bps":480060.0}},{"goal_type":"Traffic","flow_uid":6707,"goal_set":"Web","hold_period":20,"requirements":{"file_transfer_deadline_s":0.5}},{"goal_type":"Traffic","flow_uid":6708,"goal_set":"Video","hold_period":20,"requirements":{"max_latency_s":3.0,"min_throughput_bps":480060.0}},{"goal_type":"Traffic","flow_uid":6709,"goal_set":"Web","hold_period":20,"requirements":{"file_transfer_deadline_s":0.5}},{"goal_type":"Traffic","flow_uid":6710,"goal_set":"Video","hold_period":20,"requirements":{"max_latency_s":3.0,"min_throughput_bps":480060.0}},{"goal_type":"Traffic","flow_uid":6711,"goal_set":"Web","hold_period":20,"requirements":{"file_transfer_deadline_s":0.5}},{"goal_type":"Traffic","flow_uid":6712,"goal_set":"Web","hold_period":20,"requirements":{"file_transfer_deadline_s":0.5}},{"goal_type":"Traffic","flow_uid":6713,"goal_set":"Web","hold_period":20,"requirements":{"file_transfer_deadline_s":0.5}},{"goal_type":"Traffic","flow_uid":6714,"goal_set":"Web","hold_period":20,"requirements":{"file_transfer_deadline_s":0.5}},{"goal_type":"Traffic","flow_uid":6715,"goal_set":"Web","hold_period":20,"requirements":{"file_transfer_deadline_s":0.5}},{"goal_type":"Traffic","flow_uid":6716,"goal_set":"Web","hold_period":20,"requirements":{"file_transfer_deadline_s":0.5}},{"goal_type":"Traffic","flow_uid":6717,"goal_set":"Web","hold_period":20,"requirements":{"file_transfer_deadline_s":0.5}},{"goal_type":"Traffic","flow_uid":6718,"goal_set":"Web","hold_period":20,"requirements":{"file_transfer_deadline_s":0.5}},{"goal_type":"Traffic","flow_uid":6719,"goal_set":"Web","hold_period":20,"requirements":{"file_transfer_deadline_s":0.5}},{"goal_type":"Traffic","flow_uid":6720,"goal_set":"Web","hold_period":20,"requirements":{"file_transfer_deadline_s":0.5}},{"goal_type":"Traffic","flow_uid":6721,"goal_set":"Web","hold_period":20,"requirements":{"file_transfer_deadline_s":0.5}},{"goal_type":"Traffic","flow_uid":6722,"goal_set":"Web","hold_period":20,"requirements":{"file_transfer_deadline_s":0.5}},{"goal_type":"Traffic","flow_uid":6723,"goal_set":"Web","hold_period":20,"requirements":{"file_transfer_deadline_s":0.5}},{"goal_type":"Traffic","flow_uid":6724,"goal_set":"Web","hold_period":20,"requirements":{"file_transfer_deadline_s":0.5}},{"goal_type":"Traffic","flow_uid":6725,"goal_set":"Web","hold_period":20,"requirements":{"file_transfer_deadline_s":0.5}},{"goal_type":"Traffic","flow_uid":6726,"goal_set":"Web","hold_period":20,"requirements":{"file_transfer_deadline_s":0.5}},{"goal_type":"Traffic","flow_uid":6727,"goal_set":"Web","hold_period":20,"requirements":{"file_transfer_deadline_s":0.5}},{"goal_type":"Traffic","flow_uid":6728,"goal_set":"Web","hold_period":20,"requirements":{"file_transfer_deadline_s":0.5}}]}]